README.md
setup.cfg
setup.py
pymlfunc/__init__.py
pymlfunc/normxcorr2.py
pymlfunc/subind.py
pymlfunc/tictoc.py
pymlfunc.egg-info/PKG-INFO
pymlfunc.egg-info/SOURCES.txt
pymlfunc.egg-info/dependency_links.txt
pymlfunc.egg-info/requires.txt
pymlfunc.egg-info/top_level.txt
tests/__init__.py
tests/test_normxcorr2.py
tests/test_subind.py